types_aiobotocore_iot_roborunner/__init__.py
types_aiobotocore_iot_roborunner/__init__.pyi
types_aiobotocore_iot_roborunner/__main__.py
types_aiobotocore_iot_roborunner/client.py
types_aiobotocore_iot_roborunner/client.pyi
types_aiobotocore_iot_roborunner/literals.py
types_aiobotocore_iot_roborunner/literals.pyi
types_aiobotocore_iot_roborunner/paginator.py
types_aiobotocore_iot_roborunner/paginator.pyi
types_aiobotocore_iot_roborunner/py.typed
types_aiobotocore_iot_roborunner/type_defs.py
types_aiobotocore_iot_roborunner/type_defs.pyi
types_aiobotocore_iot_roborunner/version.py
types_aiobotocore_iot_roborunner-2.12.2.dist-info/LICENSE
types_aiobotocore_iot_roborunner-2.12.2.dist-info/METADATA
types_aiobotocore_iot_roborunner-2.12.2.dist-info/WHEEL
types_aiobotocore_iot_roborunner-2.12.2.dist-info/top_level.txt
types_aiobotocore_iot_roborunner-2.12.2.dist-info/RECORD
