Metadata-Version: 2.1
Name: types-aiobotocore-iot-roborunner
Version: 2.12.2
Summary: Type annotations for aiobotocore.IoTRoboRunner 2.12.2 service generated with mypy-boto3-builder 7.23.2
Home-page: https://github.com/youtype/mypy_boto3_builder
Author: Vlad Emelianov
Author-email: vlad.emelianov.nz@gmail.com
License: MIT License
Project-URL: Documentation, https://youtype.github.io/types_aiobotocore_docs/types_aiobotocore_iot_roborunner/
Project-URL: Source, https://github.com/youtype/mypy_boto3_builder
Project-URL: Tracker, https://github.com/youtype/mypy_boto3_builder/issues
Keywords: aiobotocore iot-roborunner type-annotations botocore mypy typeshed autocomplete
Classifier: Development Status :: 5 - Production/Stable
Classifier: Intended Audience :: Developers
Classifier: Environment :: Console
Classifier: License :: OSI Approved :: MIT License
Classifier: Natural Language :: English
Classifier: Operating System :: OS Independent
Classifier: Programming Language :: Python :: 3
Classifier: Programming Language :: Python :: 3.8
Classifier: Programming Language :: Python :: 3.9
Classifier: Programming Language :: Python :: 3.10
Classifier: Programming Language :: Python :: 3.11
Classifier: Programming Language :: Python :: 3.12
Classifier: Programming Language :: Python :: 3.13
Classifier: Programming Language :: Python :: 3 :: Only
Classifier: Programming Language :: Python :: Implementation :: CPython
Classifier: Typing :: Stubs Only
Requires-Python: >=3.8
License-File: LICENSE
Requires-Dist: typing-extensions >=4.1.0 ; python_version < "3.12"
